async_reolink/api/__init__.py
async_reolink/api/__version__.py
async_reolink/api/connection.py
async_reolink/api/const.py
async_reolink/api/errors.py
async_reolink/api/typings.py
async_reolink/api/ai/__init__.py
async_reolink/api/ai/typings.py
async_reolink/api/alarm/__init__.py
async_reolink/api/alarm/typings.py
async_reolink/api/commands/__init__.py
async_reolink/api/commands/ai.py
async_reolink/api/commands/alarm.py
async_reolink/api/commands/encoding.py
async_reolink/api/commands/led.py
async_reolink/api/commands/network.py
async_reolink/api/commands/ptz.py
async_reolink/api/commands/record.py
async_reolink/api/commands/security.py
async_reolink/api/commands/system.py
async_reolink/api/encoding/__init__.py
async_reolink/api/encoding/typings.py
async_reolink/api/led/__init__.py
async_reolink/api/led/typings.py
async_reolink/api/network/__init__.py
async_reolink/api/network/typings.py
async_reolink/api/ptz/__init__.py
async_reolink/api/ptz/typings.py
async_reolink/api/record/__init__.py
async_reolink/api/record/typings.py
async_reolink/api/security/__init__.py
async_reolink/api/security/typings.py
async_reolink/api/system/__init__.py
async_reolink/api/system/capabilities.py
async_reolink/api/system/typings.py
async_reolink/api/video/__init__.py
async_reolink/api/video/typings.py
async_reolink.api-0.6.6.dist-info/METADATA
async_reolink.api-0.6.6.dist-info/WHEEL
async_reolink.api-0.6.6.dist-info/top_level.txt
async_reolink.api-0.6.6.dist-info/RECORD
